{
    "os": "Linux-5.19.0-1010-nvidia-lowlatency-x86_64-with-glibc2.35",
    "python": "3.10.12",
    "heartbeatAt": "2024-09-09T23:22:05.682354",
    "startedAt": "2024-09-09T23:22:03.248367",
    "docker": null,
    "cuda": null,
    "args": [
        "--wallet.name",
        "Alice",
        "--wallet.hotkey",
        "Eve",
        "--subtensor.network",
        "test",
        "--device",
        "cuda:4",
        "--use_wandb"
    ],
    "state": "running",
    "program": "/home/ubuntu/frontend/bistro/miner.py",
    "codePathLocal": "miner.py",
    "codePath": "bistro/miner.py",
    "git": {
        "remote": "https://github.com/unconst/frontend.git",
        "commit": "a0660981f23476af1751d70673e4586879b6970c"
    },
    "email": "jake@bittensor.com",
    "root": "/home/ubuntu/frontend",
    "host": "training",
    "username": "ubuntu",
    "executable": "/home/ubuntu/frontend/venv/bin/python3",
    "cpu_count": 64,
    "cpu_count_logical": 128,
    "cpu_freq": {
        "current": 2233.7086953125,
        "min": 1500.0,
        "max": 3250.0
    },
    "cpu_freq_per_core": [
        {
            "current": 3800.152,
            "min": 1500.0,
            "max": 3250.0
        },
        {
            "current": 1515.943,
            "min": 1500.0,
            "max": 3250.0
        },
        {
            "current": 1500.0,
            "min": 1500.0,
            "max": 3250.0
        },
        {
            "current": 1519.14,
            "min": 1500.0,
            "max": 3250.0
        },
        {
            "current": 1500.0,
            "min": 1500.0,
            "max": 3250.0
        },
        {
            "current": 1520.03,
            "min": 1500.0,
            "max": 3250.0
        },
        {
            "current": 1519.102,
            "min": 1500.0,
            "max": 3250.0
        },
        {
            "current": 2367.98,
            "min": 1500.0,
            "max": 3250.0
        },
        {
            "current": 3798.984,
            "min": 1500.0,
            "max": 3250.0
        },
        {
            "current": 2166.155,
            "min": 1500.0,
            "max": 3250.0
        },
        {
            "current": 2300.0,
            "min": 1500.0,
            "max": 3250.0
        },
        {
            "current": 1500.0,
            "min": 1500.0,
            "max": 3250.0
        },
        {
            "current": 1500.0,
            "min": 1500.0,
            "max": 3250.0
        },
        {
            "current": 3799.932,
            "min": 1500.0,
            "max": 3250.0
        },
        {
            "current": 3791.421,
            "min": 1500.0,
            "max": 3250.0
        },
        {
            "current": 2171.475,
            "min": 1500.0,
            "max": 3250.0
        },
        {
            "current": 3791.745,
            "min": 1500.0,
            "max": 3250.0
        },
        {
            "current": 3798.23,
            "min": 1500.0,
            "max": 3250.0
        },
        {
            "current": 3800.134,
            "min": 1500.0,
            "max": 3250.0
        },
        {
            "current": 1500.0,
            "min": 1500.0,
            "max": 3250.0
        },
        {
            "current": 1500.0,
            "min": 1500.0,
            "max": 3250.0
        },
        {
            "current": 1500.0,
            "min": 1500.0,
            "max": 3250.0
        },
        {
            "current": 1500.0,
            "min": 1500.0,
            "max": 3250.0
        },
        {
            "current": 1500.0,
            "min": 1500.0,
            "max": 3250.0
        },
        {
            "current": 1519.721,
            "min": 1500.0,
            "max": 3250.0
        },
        {
            "current": 1500.0,
            "min": 1500.0,
            "max": 3250.0
        },
        {
            "current": 1500.0,
            "min": 1500.0,
            "max": 3250.0
        },
        {
            "current": 2165.147,
            "min": 1500.0,
            "max": 3250.0
        },
        {
            "current": 1517.197,
            "min": 1500.0,
            "max": 3250.0
        },
        {
            "current": 3786.275,
            "min": 1500.0,
            "max": 3250.0
        },
        {
            "current": 3791.485,
            "min": 1500.0,
            "max": 3250.0
        },
        {
            "current": 1500.0,
            "min": 1500.0,
            "max": 3250.0
        },
        {
            "current": 3791.49,
            "min": 1500.0,
            "max": 3250.0
        },
        {
            "current": 1500.0,
            "min": 1500.0,
            "max": 3250.0
        },
        {
            "current": 1500.0,
            "min": 1500.0,
            "max": 3250.0
        },
        {
            "current": 1500.0,
            "min": 1500.0,
            "max": 3250.0
        },
        {
            "current": 3800.152,
            "min": 1500.0,
            "max": 3250.0
        },
        {
            "current": 3250.0,
            "min": 1500.0,
            "max": 3250.0
        },
        {
            "current": 1500.0,
            "min": 1500.0,
            "max": 3250.0
        },
        {
            "current": 1500.0,
            "min": 1500.0,
            "max": 3250.0
        },
        {
            "current": 3250.0,
            "min": 1500.0,
            "max": 3250.0
        },
        {
            "current": 1500.0,
            "min": 1500.0,
            "max": 3250.0
        },
        {
            "current": 1500.0,
            "min": 1500.0,
            "max": 3250.0
        },
        {
            "current": 3250.0,
            "min": 1500.0,
            "max": 3250.0
        },
        {
            "current": 1500.0,
            "min": 1500.0,
            "max": 3250.0
        },
        {
            "current": 1500.0,
            "min": 1500.0,
            "max": 3250.0
        },
        {
            "current": 1500.0,
            "min": 1500.0,
            "max": 3250.0
        },
        {
            "current": 1500.0,
            "min": 1500.0,
            "max": 3250.0
        },
        {
            "current": 3250.0,
            "min": 1500.0,
            "max": 3250.0
        },
        {
            "current": 3799.825,
            "min": 1500.0,
            "max": 3250.0
        },
        {
            "current": 3796.739,
            "min": 1500.0,
            "max": 3250.0
        },
        {
            "current": 1500.0,
            "min": 1500.0,
            "max": 3250.0
        },
        {
            "current": 3800.139,
            "min": 1500.0,
            "max": 3250.0
        },
        {
            "current": 3250.0,
            "min": 1500.0,
            "max": 3250.0
        },
        {
            "current": 1500.0,
            "min": 1500.0,
            "max": 3250.0
        },
        {
            "current": 1500.0,
            "min": 1500.0,
            "max": 3250.0
        },
        {
            "current": 3794.597,
            "min": 1500.0,
            "max": 3250.0
        },
        {
            "current": 1500.0,
            "min": 1500.0,
            "max": 3250.0
        },
        {
            "current": 1500.0,
            "min": 1500.0,
            "max": 3250.0
        },
        {
            "current": 1500.0,
            "min": 1500.0,
            "max": 3250.0
        },
        {
            "current": 1500.0,
            "min": 1500.0,
            "max": 3250.0
        },
        {
            "current": 3250.0,
            "min": 1500.0,
            "max": 3250.0
        },
        {
            "current": 3250.0,
            "min": 1500.0,
            "max": 3250.0
        },
        {
            "current": 3795.915,
            "min": 1500.0,
            "max": 3250.0
        },
        {
            "current": 1500.0,
            "min": 1500.0,
            "max": 3250.0
        },
        {
            "current": 1500.0,
            "min": 1500.0,
            "max": 3250.0
        },
        {
            "current": 2363.806,
            "min": 1500.0,
            "max": 3250.0
        },
        {
            "current": 1500.0,
            "min": 1500.0,
            "max": 3250.0
        },
        {
            "current": 3800.109,
            "min": 1500.0,
            "max": 3250.0
        },
        {
            "current": 1519.804,
            "min": 1500.0,
            "max": 3250.0
        },
        {
            "current": 1518.646,
            "min": 1500.0,
            "max": 3250.0
        },
        {
            "current": 1519.576,
            "min": 1500.0,
            "max": 3250.0
        },
        {
            "current": 3800.14,
            "min": 1500.0,
            "max": 3250.0
        },
        {
            "current": 1500.0,
            "min": 1500.0,
            "max": 3250.0
        },
        {
            "current": 2171.521,
            "min": 1500.0,
            "max": 3250.0
        },
        {
            "current": 1500.0,
            "min": 1500.0,
            "max": 3250.0
        },
        {
            "current": 3789.062,
            "min": 1500.0,
            "max": 3250.0
        },
        {
            "current": 3250.0,
            "min": 1500.0,
            "max": 3250.0
        },
        {
            "current": 1500.0,
            "min": 1500.0,
            "max": 3250.0
        },
        {
            "current": 1500.0,
            "min": 1500.0,
            "max": 3250.0
        },
        {
            "current": 1500.0,
            "min": 1500.0,
            "max": 3250.0
        },
        {
            "current": 1500.0,
            "min": 1500.0,
            "max": 3250.0
        },
        {
            "current": 1500.0,
            "min": 1500.0,
            "max": 3250.0
        },
        {
            "current": 1500.0,
            "min": 1500.0,
            "max": 3250.0
        },
        {
            "current": 2169.639,
            "min": 1500.0,
            "max": 3250.0
        },
        {
            "current": 3798.265,
            "min": 1500.0,
            "max": 3250.0
        },
        {
            "current": 1500.0,
            "min": 1500.0,
            "max": 3250.0
        },
        {
            "current": 1500.0,
            "min": 1500.0,
            "max": 3250.0
        },
        {
            "current": 1514.489,
            "min": 1500.0,
            "max": 3250.0
        },
        {
            "current": 1500.0,
            "min": 1500.0,
            "max": 3250.0
        },
        {
            "current": 3250.0,
            "min": 1500.0,
            "max": 3250.0
        },
        {
            "current": 2171.417,
            "min": 1500.0,
            "max": 3250.0
        },
        {
            "current": 1500.0,
            "min": 1500.0,
            "max": 3250.0
        },
        {
            "current": 1500.0,
            "min": 1500.0,
            "max": 3250.0
        },
        {
            "current": 3798.294,
            "min": 1500.0,
            "max": 3250.0
        },
        {
            "current": 1519.054,
            "min": 1500.0,
            "max": 3250.0
        },
        {
            "current": 1500.0,
            "min": 1500.0,
            "max": 3250.0
        },
        {
            "current": 1500.0,
            "min": 1500.0,
            "max": 3250.0
        },
        {
            "current": 3250.0,
            "min": 1500.0,
            "max": 3250.0
        },
        {
            "current": 3250.0,
            "min": 1500.0,
            "max": 3250.0
        },
        {
            "current": 1500.0,
            "min": 1500.0,
            "max": 3250.0
        },
        {
            "current": 3250.0,
            "min": 1500.0,
            "max": 3250.0
        },
        {
            "current": 3250.0,
            "min": 1500.0,
            "max": 3250.0
        },
        {
            "current": 3250.0,
            "min": 1500.0,
            "max": 3250.0
        },
        {
            "current": 3788.767,
            "min": 1500.0,
            "max": 3250.0
        },
        {
            "current": 3250.0,
            "min": 1500.0,
            "max": 3250.0
        },
        {
            "current": 3250.0,
            "min": 1500.0,
            "max": 3250.0
        },
        {
            "current": 1500.0,
            "min": 1500.0,
            "max": 3250.0
        },
        {
            "current": 3793.88,
            "min": 1500.0,
            "max": 3250.0
        },
        {
            "current": 1500.0,
            "min": 1500.0,
            "max": 3250.0
        },
        {
            "current": 1500.0,
            "min": 1500.0,
            "max": 3250.0
        },
        {
            "current": 1500.0,
            "min": 1500.0,
            "max": 3250.0
        },
        {
            "current": 3250.0,
            "min": 1500.0,
            "max": 3250.0
        },
        {
            "current": 3250.0,
            "min": 1500.0,
            "max": 3250.0
        },
        {
            "current": 3250.0,
            "min": 1500.0,
            "max": 3250.0
        },
        {
            "current": 3250.0,
            "min": 1500.0,
            "max": 3250.0
        },
        {
            "current": 1500.0,
            "min": 1500.0,
            "max": 3250.0
        },
        {
            "current": 3250.0,
            "min": 1500.0,
            "max": 3250.0
        },
        {
            "current": 3250.0,
            "min": 1500.0,
            "max": 3250.0
        },
        {
            "current": 3250.0,
            "min": 1500.0,
            "max": 3250.0
        },
        {
            "current": 1500.0,
            "min": 1500.0,
            "max": 3250.0
        },
        {
            "current": 3250.0,
            "min": 1500.0,
            "max": 3250.0
        },
        {
            "current": 3250.0,
            "min": 1500.0,
            "max": 3250.0
        },
        {
            "current": 1517.192,
            "min": 1500.0,
            "max": 3250.0
        },
        {
            "current": 1500.0,
            "min": 1500.0,
            "max": 3250.0
        },
        {
            "current": 3250.0,
            "min": 1500.0,
            "max": 3250.0
        },
        {
            "current": 3250.0,
            "min": 1500.0,
            "max": 3250.0
        },
        {
            "current": 3250.0,
            "min": 1500.0,
            "max": 3250.0
        }
    ],
    "disk": {
        "/": {
            "total": 3519.6199798583984,
            "used": 82.0367431640625
        }
    },
    "gpu": "NVIDIA H100 PCIe",
    "gpu_count": 8,
    "memory": {
        "total": 1511.5785369873047
    }
}
